Metadata-Version: 2.1
Name: cheese-python3-api
Version: 1.0.0
Summary: An official Python3 module to query the cheese chemical space search server (https://cheese.themama.ai/)
Home-page: https://github.com/the-mama-ai/cheese-python-api
Author: The MAMA AI
Author-email: 
License: MIT
Platform: UNKNOWN
Classifier: Development Status :: 5 - Production/Stable
Classifier: Intended Audience :: Science/Research
Classifier: Topic :: Scientific/Engineering :: Chemistry
Classifier: License :: OSI Approved :: MIT License
Classifier: Programming Language :: Python :: 3.7
Classifier: Programming Language :: Python :: 3.8
Classifier: Programming Language :: Python :: 3.9
Requires-Python: >=3.7
